odmammogram/__init__.py
odmammogram/__version__.py
odmammogram/run_pipeline.py
odmammogram/run_tests.py
odmammogram/core/__configloc__.py
odmammogram/core/__init__.py
odmammogram/core/fivebhist_runner.py
odmammogram/core/outlier_detector.py
odmammogram/core/utils.py
odmammogram/core/vae.py
odmammogram/core/vae_runner.py
odmammogram/core/feature_extractor/__init__.py
odmammogram/core/feature_extractor/features.py
odmammogram/core/feature_extractor/normalizations.py
odmammogram-0.1.0.dist-info/LICENSE
odmammogram-0.1.0.dist-info/METADATA
odmammogram-0.1.0.dist-info/WHEEL
odmammogram-0.1.0.dist-info/top_level.txt
odmammogram-0.1.0.dist-info/RECORD
