Metadata-Version: 2.1
Name: odmammogram
Version: 0.1.0
Summary: Outlier Detection for Mammograms (ODM) is a Python package for medical image analysis...
Home-page: https://github.com/RyanZurrin/odmammogram
Author: Ryan Zurrin, Daniel Haehn
Author-email: Ryan Zurrin <ryan.zurrin001@umb.edu>, Daniel Haehn <daniel.haehn@umb.edu>
License: UNKNOWN
Platform: UNKNOWN
Classifier: Programming Language :: Python :: 3.9
Classifier: Development Status :: 3 - Alpha
Classifier: Intended Audience :: Developers
Classifier: Intended Audience :: Science/Research
Classifier: Intended Audience :: Education
Classifier: License :: OSI Approved :: MIT License
Classifier: Topic :: Scientific/Engineering :: Medical Science Apps.
License-File: LICENSE
Requires-Dist: matplotlib (~=3.6.2)
Requires-Dist: mahotas (~=1.4.13)
Requires-Dist: pyod
Requires-Dist: scikit-learn (~=1.2.0)
Requires-Dist: scikit-image (==0.19.2)
Requires-Dist: keras
Requires-Dist: hyperopt (~=0.2.7)
Requires-Dist: pydicom (~=2.3.1)
Requires-Dist: gdcm
Requires-Dist: pylibjpeg[all]
Requires-Dist: numpy (~=1.23.5)
Requires-Dist: tqdm (~=4.65.0)
Requires-Dist: Pillow (~=9.3.0)
Requires-Dist: pandas (~=1.5.2)
Requires-Dist: statsmodels (~=0.13.5)
Requires-Dist: tensorflow (~=2.12.0)
Requires-Dist: future (~=0.18.3)
Requires-Dist: setuptools (~=65.6.3)
